{
  "dataset_name": "Family Income and Expenditure Survey (FIES)",
  "dataset_source": "https://www.kaggle.com/datasets/grosvenpaul/family-income-and-expenditure",
  "target": "Total Household Income",
  "rows": 41544,
  "features_used": [
    "Region",
    "Total Food Expenditure",
    "Education Expenditure",
    "house_floor_area"
  ],
  "model": {
    "type": "RandomForestRegressor",
    "params": {
      "n_estimators": 40,
      "max_depth": 10,
      "random_state": 42
    }
  },
  "metrics": {
    "r2": 0.5267294661917241,
    "rmse": 190000.4167533749,
    "mae": 85367.08029652516,
    "test_size": 0.3
  },
  "training_time_utc": "2025-10-28T12:36:29.612111Z",
  "top_feature_importances": [
    {
      "name": "num__Total Food Expenditure",
      "importance": 0.670774978093692
    },
    {
      "name": "num__Education Expenditure",
      "importance": 0.13155389220868988
    },
    {
      "name": "num__house_floor_area",
      "importance": 0.11569229655440211
    },
    {
      "name": "cat__Region_VI - Western Visayas",
      "importance": 0.021833285134294656
    },
    {
      "name": "cat__Region_VIII - Eastern Visayas",
      "importance": 0.013739460542808328
    }
  ],
  "preview_columns": [
    "Region",
    "Total Food Expenditure",
    "Education Expenditure",
    "house_floor_area",
    "Total Household Income"
  ],
  "preview_rows": [
    {
      "Region": "CAR",
      "Total Food Expenditure": 117848,
      "Education Expenditure": 36200,
      "house_floor_area": 80,
      "Total Household Income": 480332
    },
    {
      "Region": "CAR",
      "Total Food Expenditure": 67766,
      "Education Expenditure": 29300,
      "house_floor_area": 42,
      "Total Household Income": 198235
    },
    {
      "Region": "CAR",
      "Total Food Expenditure": 61609,
      "Education Expenditure": 425,
      "house_floor_area": 35,
      "Total Household Income": 82785
    },
    {
      "Region": "CAR",
      "Total Food Expenditure": 78189,
      "Education Expenditure": 300,
      "house_floor_area": 30,
      "Total Household Income": 107589
    },
    {
      "Region": "CAR",
      "Total Food Expenditure": 94625,
      "Education Expenditure": 0,
      "house_floor_area": 54,
      "Total Household Income": 189322
    }
  ]
}